amd_monai/__init__.py
amd_monai-0.0.2.dist-info/METADATA
amd_monai-0.0.2.dist-info/WHEEL
amd_monai-0.0.2.dist-info/top_level.txt
amd_monai-0.0.2.dist-info/RECORD
