Metadata-Version: 2.4
Name: amd-monai
Version: 0.0.2
Summary: AI Toolkit for Healthcare Imaging
Author-email: AMD <support@amd.com>
License: See LICENSE file
Project-URL: Homepage, https://rocm.docs.amd.com/projects/monai/en/latest/
Project-URL: Documentation, https://rocm.docs.amd.com/projects/monai/en/latest/
Requires-Python: >=3.8
